[
  {
    "id": 1,
    "name": "123",
    "type": "recuperacao",
    "address": "wwwww",
    "bairro": "wwwww",
    "phone": "wwww",
    "email": "www@wwww",
    "enfermeiro": "wwwww",
    "gerente": "wwwww",
    "vacina": "Sim",
    "odonto": "Sim",
    "farmacia": "Sim",
    "responsavel": "",
    "favorite": false
  },
  {
    "id": 2,
    "name": "2",
    "type": "capne",
    "address": "2",
    "bairro": "2",
    "phone": "2",
    "email": "2@w",
    "enfermeiro": "",
    "gerente": "",
    "vacina": "Não",
    "odonto": "Não",
    "farmacia": "Não",
    "responsavel": "2",
    "favorite": false
  }
]